asciispin/__init__.py
asciispin/__main__.py
asciispin-0.0.1.dist-info/METADATA
asciispin-0.0.1.dist-info/WHEEL
asciispin-0.0.1.dist-info/top_level.txt
asciispin-0.0.1.dist-info/RECORD
