Metadata-Version: 2.1
Name: asciispin
Version: 0.0.1
Summary: the simple, but useful asciispin
Home-page: UNKNOWN
Author: ezrashare31
License: UNKNOWN
Platform: UNKNOWN
